opentelemetry/py.typed
opentelemetry/exporter/cloud_monitoring/__init__.py
opentelemetry/exporter/cloud_monitoring/environment_variables.py
opentelemetry/exporter/cloud_monitoring/version.py
opentelemetry_exporter_gcp_monitoring-1.8.0a0.dist-info/LICENSE
opentelemetry_exporter_gcp_monitoring-1.8.0a0.dist-info/METADATA
opentelemetry_exporter_gcp_monitoring-1.8.0a0.dist-info/WHEEL
opentelemetry_exporter_gcp_monitoring-1.8.0a0.dist-info/entry_points.txt
opentelemetry_exporter_gcp_monitoring-1.8.0a0.dist-info/top_level.txt
opentelemetry_exporter_gcp_monitoring-1.8.0a0.dist-info/RECORD
